.VERSION
AUTHORS.rst
CONTRIBUTING.rst
HISTORY.rst
LICENSE
MANIFEST.in
Pipfile
Pipfile.lock
README.rst
USAGE.rst
dev-requirements.txt
requirements.txt
setup.cfg
setup.py
awsauthenticationlib/.VERSION
awsauthenticationlib/AUTHORS.rst
awsauthenticationlib/CONTRIBUTING.rst
awsauthenticationlib/HISTORY.rst
awsauthenticationlib/LICENSE
awsauthenticationlib/Pipfile
awsauthenticationlib/Pipfile.lock
awsauthenticationlib/README.rst
awsauthenticationlib/USAGE.rst
awsauthenticationlib/__init__.py
awsauthenticationlib/_version.py
awsauthenticationlib/awsauthenticationlib.py
awsauthenticationlib/awsauthenticationlibexceptions.py
awsauthenticationlib/dev-requirements.txt
awsauthenticationlib/requirements.txt
awsauthenticationlib/utils.py
awsauthenticationlib.egg-info/PKG-INFO
awsauthenticationlib.egg-info/SOURCES.txt
awsauthenticationlib.egg-info/dependency_links.txt
awsauthenticationlib.egg-info/not-zip-safe
awsauthenticationlib.egg-info/requires.txt
awsauthenticationlib.egg-info/top_level.txt
awsauthenticationlib/__pycache__/__init__.cpython-37.pyc
awsauthenticationlib/__pycache__/_version.cpython-37.pyc
awsauthenticationlib/__pycache__/awsauthenticationlib.cpython-37.pyc
awsauthenticationlib/__pycache__/awsauthenticationlibexceptions.cpython-37.pyc
awsauthenticationlib/__pycache__/utils.cpython-37.pyc
docs/Makefile
docs/authors.rst
docs/conf.py
docs/contributing.rst
docs/history.rst
docs/index.rst
docs/installation.rst
docs/readme.rst
docs/usage.rst