Metadata-Version: 1.1
Name: awsauthenticationlib
Version: 0.5.0
Summary: A library providing pre signed urls and valid sessions for some aws services that still do not present an api.
Home-page: https://github.com/schubergphilis/awsauthenticationlib.git
Author: Costas Tyfoxylos
Author-email: ctyfoxylos@schubergphilis.com
License: MIT
Keywords: awsauthenticationlib aws authentication pre signed sessions
Platform: UNKNOWN
Classifier: Development Status :: 4 - Beta
Classifier: Intended Audience :: Developers
Classifier: License :: OSI Approved :: MIT License
Classifier: Natural Language :: English
Classifier: Programming Language :: Python :: 3.7
